oliver_prefect_kedro_ii/__init__.py
oliver_prefect_kedro_ii/infrastructure.py
oliver_prefect_kedro_ii/register.py
oliver_prefect_kedro_ii-0.2.6.dist-info/METADATA
oliver_prefect_kedro_ii-0.2.6.dist-info/WHEEL
oliver_prefect_kedro_ii-0.2.6.dist-info/top_level.txt
oliver_prefect_kedro_ii-0.2.6.dist-info/RECORD
